ph_confer/__init__.py
ph_confer/cli.py
ph_confer/exceptions.py
ph_confer/key_value_bridge.py
ph_confer/template_manager.py
ph_confer/within_template_config.py
ph_confer-1.2.9.dist-info/LICENSE.md
ph_confer-1.2.9.dist-info/METADATA
ph_confer-1.2.9.dist-info/WHEEL
ph_confer-1.2.9.dist-info/entry_points.txt
ph_confer-1.2.9.dist-info/top_level.txt
ph_confer-1.2.9.dist-info/zip-safe
ph_confer-1.2.9.dist-info/RECORD
