Metadata-Version: 2.1
Name: ph-confer
Version: 1.2.9
Summary: A tool to automatically template configurations from a key-value store.
Home-page: https://www.parsehub.com
Author: ParseHub
Author-email: serge@parsehub.com
License: LGPLv3
Keywords: sysadmin development tools configuration
Platform: UNKNOWN
Classifier: Development Status :: 5 - Production/Stable
Classifier: Intended Audience :: Developers
Classifier: Topic :: Utilities
Classifier: License :: OSI Approved :: GNU Lesser General Public License v3 (LGPLv3)
Classifier: Programming Language :: Python :: 3
Classifier: Programming Language :: Python :: 3.3
Classifier: Programming Language :: Python :: 3.4
Classifier: Programming Language :: Python :: 3.5
Classifier: Programming Language :: Python :: 3.8
Classifier: Programming Language :: Python :: 3.9
License-File: LICENSE.md
Requires-Dist: mako (==1.2.3)
Requires-Dist: python-etcd (==0.4.3)
